{
"autoplayBgm":false,"autoplayBgs":false,"battleback1Name":"","battleback2Name":"","bgm":{"name":"","pan":0,"pitch":100,"volume":90},"bgs":{"name":"","pan":0,"pitch":100,"volume":90},"disableDashing":false,"displayName":"","encounterList":[],"encounterStep":30,"height":13,"note":"","parallaxLoopX":false,"parallaxLoopY":false,"parallaxName":"","parallaxShow":true,"parallaxSx":0,"parallaxSy":0,"scrollType":0,"specifyBattleback":false,"tilesetId":1,"width":17,
"data":[0,0,0,0,0,0,0,0,0,0,0,0,0,0,0,0,0,0,0,0,0,0,0,0,0,0,0,0,0,0,0,0,0,0,0,0,0,0,0,0,0,0,0,0,0,0,0,0,0,0,0,0,0,0,0,0,0,0,0,0,0,0,0,0,0,0,0,0,0,0,0,0,0,0,0,0,0,0,0,0,0,0,0,0,0,0,0,0,0,0,0,0,0,0,0,0,0,0,0,0,0,0,0,0,0,0,0,0,0,0,0,0,0,0,0,0,0,0,0,0,0,0,0,0,0,0,0,0,0,0,0,0,0,0,0,0,0,0,0,0,0,0,0,0,0,0,0,0,0,0,0,0,0,0,0,0,0,0,0,0,0,0,0,0,0,0,0,0,0,0,0,0,0,0,0,0,0,0,0,0,0,0,0,0,0,0,0,0,0,0,0,0,0,0,0,0,0,0,0,0,0,0,0,0,0,0,0,0,0,0,0,0,0,0,0,0,0,0,0,0,0,0,0,0,0,0,0,0,0,0,0,0,0,0,0,0,0,0,0,0,0,0,0,0,0,0,0,0,0,0,0,0,0,0,0,0,0,0,0,0,0,0,0,0,0,0,0,0,0,0,0,0,0,0,0,0,0,0,0,0,0,0,0,0,0,0,0,0,0,0,0,0,0,0,0,0,0,0,0,0,0,0,0,0,0,0,0,0,0,0,0,0,0,0,0,0,0,0,0,0,0,0,0,0,0,0,0,0,0,0,0,0,0,0,0,0,0,0,0,0,0,0,0,0,0,0,0,0,0,0,0,0,0,0,0,0,0,0,0,0,0,0,0,0,0,0,0,0,0,0,0,0,0,0,0,0,0,0,0,0,0,0,0,0,0,0,0,0,0,0,0,0,0,0,0,0,0,0,0,0,0,0,0,0,0,0,0,0,0,0,0,0,0,0,0,0,0,0,0,0,0,0,0,0,0,0,0,0,0,0,0,0,0,0,0,0,0,0,0,0,0,0,0,0,0,0,0,0,0,0,0,0,0,0,0,0,0,0,0,0,0,0,0,0,0,0,0,0,0,0,0,0,0,0,0,0,0,0,0,0,0,0,0,0,0,0,0,0,0,0,0,0,0,0,0,0,0,0,0,0,0,0,0,0,0,0,0,0,0,0,0,0,0,0,0,0,0,0,0,0,0,0,0,0,0,0,0,0,0,0,0,0,0,0,0,0,0,0,0,0,0,0,0,0,0,0,0,0,0,0,0,0,0,0,0,0,0,0,0,0,0,0,0,0,0,0,0,0,0,0,0,0,0,0,0,0,0,0,0,0,0,0,0,0,0,0,0,0,0,0,0,0,0,0,0,0,0,0,0,0,0,0,0,0,0,0,0,0,0,0,0,0,0,0,0,0,0,0,0,0,0,0,0,0,0,0,0,0,0,0,0,0,0,0,0,0,0,0,0,0,0,0,0,0,0,0,0,0,0,0,0,0,0,0,0,0,0,0,0,0,0,0,0,0,0,0,0,0,0,0,0,0,0,0,0,0,0,0,0,0,0,0,0,0,0,0,0,0,0,0,0,0,0,0,0,0,0,0,0,0,0,0,0,0,0,0,0,0,0,0,0,0,0,0,0,0,0,0,0,0,0,0,0,0,0,0,0,0,0,0,0,0,0,0,0,0,0,0,0,0,0,0,0,0,0,0,0,0,0,0,0,0,0,0,0,0,0,0,0,0,0,0,0,0,0,0,0,0,0,0,0,0,0,0,0,0,0,0,0,0,0,0,0,0,0,0,0,0,0,0,0,0,0,0,0,0,0,0,0,0,0,0,0,0,0,0,0,0,0,0,0,0,0,0,0,0,0,0,0,0,0,0,0,0,0,0,0,0,0,0,0,0,0,0,0,0,0,0,0,0,0,0,0,0,0,0,0,0,0,0,0,0,0,0,0,0,0,0,0,0,0,0,0,0,0,0,0,0,0,0,0,0,0,0,0,0,0,0,0,0,0,0,0,0,0,0,0,0,0,0,0,0,0,0,0,0,0,0,0,0,0,0,0,0,0,0,0,0,0,0,0,0,0,0,0,0,0,0,0,0,0,0,0,0,0,0,0,0,0,0,0,0,0,0,0,0,0,0,0,0,0,0,0,0,0,0,0,0,0,0,0,0,0,0,0,0,0,0,0,0,0,0,0,0,0,0,0,0,0,0,0,0,0,0,0,0,0,0,0,0,0,0,0,0,0,0,0,0,0,0,0,0,0,0,0,0,0,0,0,0,0,0,0,0,0,0,0,0,0,0,0,0,0,0,0,0,0,0,0,0,0,0,0,0,0,0,0,0,0,0,0,0,0,0,0,0,0,0,0,0,0,0,0,0,0,0,0,0,0,0,0,0,0,0,0,0,0,0,0,0,0,0,0,0,0,0,0,0,0,0,0,0,0,0,0,0,0,0,0,0,0,0,0,0,0,0,0,0,0,0,0,0,0,0,0,0,0,0,0,0,0,0,0,0,0,0,0,0,0,0,0,0,0,0,0,0,0,0,0,0,0,0,0,0,0,0,0,0,0,0,0,0,0,0,0,0,0,0,0,0,0,0,0,0,0,0,0,0,0,0,0,0,0,0,0,0,0,0,0,0,0,0,0,0,0,0,0,0,0,0,0,0,0,0,0,0,0,0,0,0,0,0,0,0,0,0,0,0,0,0,0,0,0,0,0,0,0,0,0,0,0,0,0,0,0,0,0,0,0,0,0,0,0,0,0,0,0,0,0,0,0,0,0,0,0,0,0,0,0,0,0,0,0,0,0,0,0,0,0,0,0,0,0,0,0,0,0,0,0,0,0,0,0,0,0,0,0,0,0,0,0,0,0,0,0,0,0,0,0,0,0,0,0,0,0,0,0,0,0,0,0,0,0,0,0,0,0,0,0,0,0,0,0,0,0,0,0,0,0,0,0,0,0,0,0,0,0,0,0,0,0,0,0,0,0,0,0,0,0,0,0,0,0,0,0,0],
"events":[
null,
{"id":1,"name":"EV001","note":"","pages":[{"conditions":{"actorId":1,"actorValid":false,"itemId":1,"itemValid":false,"selfSwitchCh":"A","selfSwitchValid":false,"switch1Id":1,"switch1Valid":false,"switch2Id":1,"switch2Valid":false,"variableId":1,"variableValid":false,"variableValue":0},"directionFix":false,"image":{"characterIndex":0,"characterName":"","direction":2,"pattern":0,"tileId":0},"list":[{"code":230,"indent":0,"parameters":[10]},{"code":231,"indent":0,"parameters":[1,"cg19",0,0,0,0,100,100,255,0]},{"code":101,"indent":0,"parameters":["",0,0,2]},{"code":401,"indent":0,"parameters":["这地道居然下面还有一层，比想象中要大啊……"]},{"code":250,"indent":0,"parameters":[{"name":"Close3","volume":40,"pitch":100,"pan":0}]},{"code":242,"indent":0,"parameters":[3]},{"code":231,"indent":0,"parameters":[1,"cg20",0,0,0,0,100,100,255,0]},{"code":230,"indent":0,"parameters":[90]},{"code":231,"indent":0,"parameters":[1,"cg21",0,0,0,0,100,100,255,0]},{"code":101,"indent":0,"parameters":["",0,0,2]},{"code":401,"indent":0,"parameters":["怎么会！！来时的路突然被栏杆封住了！！"]},{"code":101,"indent":0,"parameters":["",0,0,2]},{"code":401,"indent":0,"parameters":["看来只能先继续往地道深处走了……"]},{"code":235,"indent":0,"parameters":[1]},{"code":230,"indent":0,"parameters":[60]},{"code":250,"indent":0,"parameters":[{"name":"Laser1","volume":45,"pitch":80,"pan":0}]},{"code":225,"indent":0,"parameters":[5,5,30,false]},{"code":231,"indent":0,"parameters":[1,"cg22",0,0,0,0,100,100,255,0]},{"code":101,"indent":0,"parameters":["",0,0,2]},{"code":401,"indent":0,"parameters":["箭、箭从墙壁里飞出来了啊啊啊！！！"]},{"code":101,"indent":0,"parameters":["",0,0,2]},{"code":401,"indent":0,"parameters":["弗、弗兰克你冷静一点，不就是一支箭嘛！"]},{"code":230,"indent":0,"parameters":[40]},{"code":250,"indent":0,"parameters":[{"name":"Miss","volume":45,"pitch":80,"pan":0}]},{"code":225,"indent":0,"parameters":[5,5,30,false]},{"code":231,"indent":0,"parameters":[1,"cg23",0,0,0,0,100,100,255,0]},{"code":101,"indent":0,"parameters":["",0,0,2]},{"code":401,"indent":0,"parameters":["啊！！！有谁的眼珠子掉下来了啊啊啊啊！！！"]},{"code":101,"indent":0,"parameters":["",0,0,2]},{"code":401,"indent":0,"parameters":["这是眼球的模型吗？！！"]},{"code":401,"indent":0,"parameters":["也太逼真了吧好恶心啊！！！"]},{"code":230,"indent":0,"parameters":[40]},{"code":225,"indent":0,"parameters":[5,5,30,false]},{"code":250,"indent":0,"parameters":[{"name":"Liquid","volume":90,"pitch":100,"pan":0}]},{"code":231,"indent":0,"parameters":[1,"cg24",0,0,0,0,100,100,255,0]},{"code":101,"indent":0,"parameters":["",0,0,2]},{"code":401,"indent":0,"parameters":["墙壁流血了啊啊啊啊啊啊！！！"]},{"code":101,"indent":0,"parameters":["",0,0,2]},{"code":401,"indent":0,"parameters":["不是，这个出血量也太不妙了吧啊啊啊！！！"]},{"code":230,"indent":0,"parameters":[40]},{"code":235,"indent":0,"parameters":[1]},{"code":230,"indent":0,"parameters":[60]},{"code":231,"indent":0,"parameters":[1,"弗兰树7",0,0,0,0,100,100,255,0]},{"code":101,"indent":0,"parameters":["",0,0,2]},{"code":401,"indent":0,"parameters":["呜呜呜……我是一棵树……"]},{"code":231,"indent":0,"parameters":[1,"弗兰树7",0,0,0,0,100,100,150,0]},{"code":231,"indent":0,"parameters":[2,"库洛4",0,0,0,0,100,100,255,0]},{"code":101,"indent":0,"parameters":["",0,0,2]},{"code":401,"indent":0,"parameters":["我是画框我是画框我是画框……"]},{"code":231,"indent":0,"parameters":[3,"瑞琪2",0,0,0,0,100,100,255,0]},{"code":231,"indent":0,"parameters":[2,"库洛4",0,0,0,0,100,100,150,0]},{"code":101,"indent":0,"parameters":["",0,0,2]},{"code":401,"indent":0,"parameters":["你们两个没事吧……？"]},{"code":401,"indent":0,"parameters":["我们已经从楼梯上下来了哦。"]},{"code":231,"indent":0,"parameters":[3,"瑞琪2",0,0,0,0,100,100,150,0]},{"code":231,"indent":0,"parameters":[2,"库洛3",0,0,0,0,100,100,255,0]},{"code":101,"indent":0,"parameters":["",0,0,2]},{"code":401,"indent":0,"parameters":["终于到头了……"]},{"code":401,"indent":0,"parameters":["这楼梯上的机关怎么会这么多啊！"]},{"code":231,"indent":0,"parameters":[2,"库洛3",0,0,0,0,100,100,150,0]},{"code":231,"indent":0,"parameters":[3,"瑞琪2",0,0,0,0,100,100,255,0]},{"code":101,"indent":0,"parameters":["",0,0,2]},{"code":401,"indent":0,"parameters":["感觉像是地道的主人不想让其他人随随便便来到这里一样……"]},{"code":401,"indent":0,"parameters":["或许我们误入了一个很重要的设施。"]},{"code":101,"indent":0,"parameters":["",0,0,2]},{"code":401,"indent":0,"parameters":["不过既然回去的楼梯已经被封住了，"]},{"code":401,"indent":0,"parameters":["从你们两个的样子来看应该也一时半会儿不想靠近那边了，"]},{"code":401,"indent":0,"parameters":["我们还是先看看这附近有什么东西吧。"]},{"code":235,"indent":0,"parameters":[1]},{"code":235,"indent":0,"parameters":[2]},{"code":235,"indent":0,"parameters":[3]},{"code":250,"indent":0,"parameters":[{"name":"Move1","volume":40,"pitch":90,"pan":0}]},{"code":201,"indent":0,"parameters":[0,8,0,8,0,0]},{"code":0,"indent":0,"parameters":[]}],"moveFrequency":3,"moveRoute":{"list":[{"code":0,"parameters":[]}],"repeat":true,"skippable":false,"wait":false},"moveSpeed":3,"moveType":0,"priorityType":0,"stepAnime":false,"through":false,"trigger":3,"walkAnime":true}],"x":0,"y":12}
]
}